GPopt/BOstopping.py
GPopt/GPOpt.py
GPopt/GeneralizationOpt.py
GPopt/__init__.py
GPopt/config.py
GPopt/genericcv.py
GPopt/utils/__init__.py
GPopt/utils/nodesimulation.py
GPopt/utils/progress_bar.py
GPopt/utils/sobol_lib.py
gpopt-0.10.1.dist-info/licenses/LICENSE
gpopt-0.10.1.dist-info/METADATA
gpopt-0.10.1.dist-info/WHEEL
gpopt-0.10.1.dist-info/top_level.txt
gpopt-0.10.1.dist-info/RECORD
