Metadata-Version: 2.4
Name: GPopt
Version: 0.10.1
Summary: Bayesian Optimization using Gaussian Process Regression
Home-page: https://github.com/thierrymoudiki/GPopt
Download-URL: https://github.com/thierrymoudiki/GPopt/tarball/0.10.1
Author: Thierry Moudiki
Author-email: thierry.moudiki@gmail.com
License: BSD
Classifier: Development Status :: 3 - Alpha
Classifier: Intended Audience :: Developers
Classifier: Programming Language :: Python :: 3
License-File: LICENSE
Requires-Dist: joblib
Requires-Dist: matplotlib
Requires-Dist: nnetsauce
Requires-Dist: numpy
Requires-Dist: pandas
Requires-Dist: SALib
Requires-Dist: scipy
Requires-Dist: scikit-learn
Requires-Dist: threadpoolctl
Requires-Dist: tqdm
Dynamic: author
Dynamic: author-email
Dynamic: classifier
Dynamic: description
Dynamic: download-url
Dynamic: home-page
Dynamic: keywords
Dynamic: license
Dynamic: license-file
Dynamic: requires-dist
Dynamic: summary
